tf_idem_auto/conf.py
tf_idem_auto/scripts.py
tf_idem_auto/version.py
tf_idem_auto/tf_idem_auto/arg_binding_params_resolver.py
tf_idem_auto/tf_idem_auto/idem_describe.py
tf_idem_auto/tf_idem_auto/init.py
tf_idem_auto/tf_idem_auto/process_tf_to_sls.py
tf_idem_auto/tf_idem_auto/sls_file_filter.py
tf_idem_auto/tf_idem_auto/tf_sls.py
tf_idem_auto/tf_idem_auto/tf_state_data_processor.py
tf_idem_auto/tf_idem_auto/utils.py
tf_idem_auto-0.1.3.dist-info/LICENSE
tf_idem_auto-0.1.3.dist-info/METADATA
tf_idem_auto-0.1.3.dist-info/WHEEL
tf_idem_auto-0.1.3.dist-info/entry_points.txt
tf_idem_auto-0.1.3.dist-info/top_level.txt
tf_idem_auto-0.1.3.dist-info/RECORD
