Metadata-Version: 2.1
Name: tf-idem-auto
Version: 0.1.3
Summary: UNKNOWN
Home-page: https://gitlab.com/apriyank/tf-idem-auto
Author: VMware Inc.
Author-email: apriyank@vmware.com
License: UNKNOWN
Platform: UNKNOWN
Classifier: Environment :: Console
Classifier: Intended Audience :: Developers
Classifier: Intended Audience :: Information Technology
Classifier: Intended Audience :: System Administrators
Classifier: Operating System :: OS Independent
Classifier: Programming Language :: Python
Classifier: Programming Language :: Python :: 3.7
Classifier: Programming Language :: Python :: 3.8
Classifier: Programming Language :: Python :: 3.9
Classifier: Programming Language :: Python :: 3.10
Classifier: Development Status :: 5 - Production/Stable
Requires-Python: >=3.7
License-File: LICENSE
Requires-Dist: pop (>=17.0)
Requires-Dist: boto3 (>=1.20.24)
Requires-Dist: idem (==18.6.1)
Requires-Dist: python-hcl2 (>=3.0.5)
Requires-Dist: ruamel.yaml (==0.17.4)
